pyctlops/__init__.py
pyctlops/pyctlops.py
pyctlops-0.1.dist-info/LICENSE
pyctlops-0.1.dist-info/METADATA
pyctlops-0.1.dist-info/WHEEL
pyctlops-0.1.dist-info/top_level.txt
pyctlops-0.1.dist-info/RECORD
